odoo/addons/product_refund_account/README.rst
odoo/addons/product_refund_account/__init__.py
odoo/addons/product_refund_account/__manifest__.py
odoo/addons/product_refund_account/i18n/es.po
odoo/addons/product_refund_account/i18n/l10n_es_product_refund_account.pot
odoo/addons/product_refund_account/i18n/product_refund_account.pot
odoo/addons/product_refund_account/models/__init__.py
odoo/addons/product_refund_account/models/account_invoice.py
odoo/addons/product_refund_account/models/account_invoice_line.py
odoo/addons/product_refund_account/models/product_category.py
odoo/addons/product_refund_account/models/product_template.py
odoo/addons/product_refund_account/readme/CONTRIBUTORS.rst
odoo/addons/product_refund_account/readme/DESCRIPTION.rst
odoo/addons/product_refund_account/readme/USAGE.rst
odoo/addons/product_refund_account/static/description/icon.png
odoo/addons/product_refund_account/static/description/index.html
odoo/addons/product_refund_account/tests/__init__.py
odoo/addons/product_refund_account/tests/test_account_refund.py
odoo/addons/product_refund_account/views/product_category_views.xml
odoo/addons/product_refund_account/views/product_template_views.xml
odoo12_addon_product_refund_account-12.0.1.0.1.dist-info/METADATA
odoo12_addon_product_refund_account-12.0.1.0.1.dist-info/WHEEL
odoo12_addon_product_refund_account-12.0.1.0.1.dist-info/top_level.txt
odoo12_addon_product_refund_account-12.0.1.0.1.dist-info/RECORD
